imports_database_page/03-imports_database_page.omero
imports_database_page/__init__.py
imports_database_page/apps.py
imports_database_page/setup_integration.py
imports_database_page/urls.py
imports_database_page/views.py
imports_database_page/templates/importsdatabase/webclient_plugins/imports_database_page.html
omero_imports_database_page-0.0.21.dist-info/LICENSE
omero_imports_database_page-0.0.21.dist-info/METADATA
omero_imports_database_page-0.0.21.dist-info/WHEEL
omero_imports_database_page-0.0.21.dist-info/entry_points.txt
omero_imports_database_page-0.0.21.dist-info/top_level.txt
omero_imports_database_page-0.0.21.dist-info/RECORD
