Metadata-Version: 2.1
Name: omero-imports-database-page
Version: 0.0.21
Summary: A Python plugin for OMERO.web to display imports database page
Home-page: https://github.com/Cellular-Imaging-Amsterdam-UMC/omero-imports-database-page
Author: Cellular Imaging Amsterdam UMC
Author-email: rrosas@amsterdamumc.nl
License: AGPL-3.0
Download-URL: https://github.com/Cellular-Imaging-Amsterdam-UMC/omero-imports-database-page/archive/refs/heads/main.zip
Keywords: OMERO.web,plugin,imports database
Platform: UNKNOWN
Classifier: Development Status :: 3 - Alpha
Classifier: Environment :: Web Environment
Classifier: Framework :: Django
Classifier: Intended Audience :: Developers
Classifier: Natural Language :: English
Classifier: Operating System :: OS Independent
Classifier: Programming Language :: Python :: 3
Classifier: Topic :: Internet :: WWW/HTTP
Classifier: Topic :: Internet :: WWW/HTTP :: Dynamic Content
Requires-Python: >=3
Requires-Dist: omero-web >=5.6.0
Requires-Dist: pyjwt
